hivemind_listener/__init__.py
hivemind_listener/protocol.py
hivemind_listener/transformers.py
hivemind_listener/version.py
hivemind_listener-2.0.0.dist-info/METADATA
hivemind_listener-2.0.0.dist-info/WHEEL
hivemind_listener-2.0.0.dist-info/entry_points.txt
hivemind_listener-2.0.0.dist-info/top_level.txt
hivemind_listener-2.0.0.dist-info/RECORD
